{
    "DNDConfig": null,
    "_height_": {
        "type": "string",
        "value": "42dp"
    },
    "_left_": {
        "type": "string",
        "value": "0dp"
    },
    "_margin_": [
        0,
        0,
        0,
        0
    ],
    "_orientation_": 6,
    "_padding_": [
        0,
        0,
        0,
        0
    ],
    "_percent_": true,
    "_skin_": "s998494fecea47c08bf16347a785b5d9",
    "_top_": {
        "type": "string",
        "value": "0dp"
    },
    "_width_": {
        "type": "string",
        "value": "100%"
    },
    "allboxes": [],
    "canUpdateUI": true,
    "children": [
        "flxIntrumentTabletHeading",
        "CopyflxSeparator0e6aaa975432147"
    ],
    "clipbounds": true,
    "containerweight": 100,
    "enablescrolling": true,
    "id": "flxHeadingTabletInstrument",
    "info": null,
    "iscustomlayout": false,
    "isvisible": true,
    "kuid": "fac1106e5ad347ddab364b6f67a50791",
    "layouttype": 3,
    "name": "kony.ui.FlexContainer",
    "parent": "flxInstrument",
    "pf": "userwidgetmodel",
    "retaincontentalignment": false,
    "retainflexpositionproperties": false,
    "retainflowhorizontalalignment": false,
    "snapgridsize": 10,
    "snaptogrid": true,
    "wType": "FlexContainer",
    "widgetalignment": 1,
    "zindex": 1
}