{
    "DNDConfig": null,
    "_height_": {
        "type": "string",
        "value": "42dp"
    },
    "_left_": {
        "type": "string",
        "value": "0dp"
    },
    "_margin_": [
        0,
        0,
        0,
        0
    ],
    "_orientation_": 6,
    "_padding_": [
        0,
        0,
        0,
        0
    ],
    "_percent_": true,
    "_skin_": "sd3ac82253ad487098482e066a19fdd5",
    "_top_": {
        "type": "string",
        "value": "0dp"
    },
    "_width_": {
        "type": "string",
        "value": "100%"
    },
    "allboxes": [],
    "canUpdateUI": true,
    "children": [
        "flxInstrumentHeading",
        "flxCurrencyHeading",
        "flxLatestHeading",
        "flxChangeHeading",
        "flxDateTimeHeading",
        "flxBidHeading",
        "flxAskHeading",
        "flxVolumeHeading",
        "flxDotsHeading"
    ],
    "clipbounds": true,
    "containerweight": 100,
    "enablescrolling": true,
    "id": "flxHeadings",
    "info": null,
    "iscustomlayout": false,
    "isvisible": true,
    "kuid": "bc3b836aaab94791bd552dbedb1e314a",
    "layouttype": 3,
    "name": "kony.ui.FlexContainer",
    "parent": "flxWatchlistSegment",
    "pf": "userwidgetmodel",
    "retaincontentalignment": false,
    "retainflexpositionproperties": false,
    "retainflowhorizontalalignment": false,
    "snapgridsize": 10,
    "snaptogrid": true,
    "wType": "FlexContainer",
    "widgetalignment": 1,
    "zindex": 1
}