{
    "DNDConfig": null,
    "_height_": {
        "type": "string",
        "value": "42dp"
    },
    "_left_": {
        "type": "string",
        "value": "74.50%"
    },
    "_margin_": [
        0,
        0,
        0,
        0
    ],
    "_orientation_": 6,
    "_padding_": [
        0,
        0,
        0,
        0
    ],
    "_percent_": true,
    "_right_": {
        "type": "string",
        "value": "20.50%"
    },
    "_skin_": "s4915538d4cf40958ad626d141b3a196",
    "_top_": {
        "type": "string",
        "value": "0"
    },
    "_width_": {
        "type": "string",
        "value": "15%"
    },
    "allboxes": [],
    "autogrowmode": 0,
    "canUpdateUI": true,
    "centery": {
        "type": "string",
        "value": "50%"
    },
    "children": [
        "lblRowCoulmn4Key",
        "lblRowCoulmn4Value"
    ],
    "clipbounds": false,
    "containerId": true,
    "containerweight": 100,
    "enablescrolling": true,
    "id": "flxRowColumn4",
    "info": null,
    "iscustomlayout": false,
    "isvisible": true,
    "kuid": "fe0edc91588744cebb7457132e108b4d",
    "layouttype": 4,
    "name": "kony.ui.FlexContainer",
    "parent": "flxDetailsRow1",
    "pf": "segSweepListingTemp",
    "retaincontentalignment": false,
    "retainflexpositionproperties": false,
    "retainflowhorizontalalignment": false,
    "snapgridsize": 10,
    "snaptogrid": true,
    "wType": "FlexContainer",
    "widgetalignment": 1
}