{
    "@class": "com.kony.gen.viz.model.component.KVizRichText",
    "DNDConfig": null,
    "_bottom_": {
        "type": "string",
        "value": "16px"
    },
    "_height_": {
        "type": "ref",
        "value": "preferred"
    },
    "_left_": {
        "type": "string",
        "value": "0dp"
    },
    "_margin_": [
        0,
        0,
        0,
        0
    ],
    "_padding_": [
        0,
        0,
        0,
        0
    ],
    "_right_": {
        "type": "string",
        "value": "0px"
    },
    "_skin_": "sf57df0e6e8e40878b77b593dbd2997a",
    "_text_": "left Value",
    "_top_": {
        "type": "string",
        "value": "6dp"
    },
    "_wrapping_": 2,
    "accessibilityconfig": {
        "a11yLabel": "left Value"
    },
    "canUpdateUI": true,
    "containerweight": 100,
    "contentalignment": 1,
    "id": "rtxLeftValueAccount1",
    "info": null,
    "isvisible": true,
    "kuid": "i4e76e1767294523adba26b2729a9c17",
    "name": "kony.ui.RichText",
    "parent": "flxLeftKeyValue1",
    "pf": "frmAccountInfoForInboundTransfer",
    "wType": "RichText",
    "widgetalignment": 5,
    "zindex": 1
}