{
    "@class": "com.kony.gen.viz.model.component.KVizTextBox2",
    "DNDConfig": null,
    "_height_": {
        "type": "string",
        "value": "84%"
    },
    "_left_": {
        "type": "string",
        "value": "15px"
    },
    "_margin_": [
        0,
        0,
        0,
        0
    ],
    "_padding_": [
        0,
        0,
        0,
        0
    ],
    "_placeholder_": "",
    "_right_": {
        "type": "string",
        "value": "2px"
    },
    "_skin_": "sb36cebb3a3a4b5fb859ba26e90ecaaa",
    "_text_": "",
    "_width_": {
        "type": "ref",
        "value": "preferred"
    },
    "accessibilityconfig": {
        "a11yARIA": {
            "aria-labelledby": "lblUsername",
            "aria-required": true
        }
    },
    "autocapitalize": "none",
    "autocomplete": false,
    "autocorrect": false,
    "autofilter": false,
    "canUpdateUI": true,
    "centery": {
        "type": "string",
        "value": "50%"
    },
    "containerheight": "",
    "containerheightmode": 1,
    "containerweight": 100,
    "contentalignment": 4,
    "desktopweb": {
        "placeholderSkin": "s458a088af4444a398ca9fbe1057d03b",
        "psp": {}
    },
    "focusskin": null,
    "id": "tbxUserName",
    "info": null,
    "isvisible": true,
    "keyboardtype": "A",
    "kiosk": {
        "psp": {
            "toolTip": ""
        }
    },
    "kuid": "cef1f461eaf44232b61990f5f5c093d7",
    "maxtextlength": "",
    "mode": "A",
    "name": "kony.ui.TextBox2",
    "paddinginpixel": false,
    "parent": "flxUserName",
    "pf": "userwidgetmodel",
    "placeholderi18n": "i18n.LoginActivation.EnterUsername",
    "placeholderskin": "s039301545174ce686ecaec59a9e23ad",
    "securetextentry": false,
    "textinputmode": "A",
    "viewtype": "default",
    "wType": "TextField",
    "zindex": 1
}