{
    "@class": "com.kony.gen.viz.model.component.KVizLabel",
    "DNDConfig": null,
    "_height_": {
        "type": "string",
        "value": "8dp"
    },
    "_left_": {
        "type": "string",
        "value": "0dp"
    },
    "_margin_": [
        1,
        1,
        1,
        1
    ],
    "_padding_": [
        0,
        0,
        5,
        0
    ],
    "_skin_": "sa098ff3ac6d432cb774630c55fd4152",
    "_text_": "",
    "_width_": {
        "type": "string",
        "value": "8dp"
    },
    "_wrapping_": 2,
    "accessibilityconfig": {
        "a11yLabel": "05/30/2017"
    },
    "android": {
        "textStyle": {
            "letterSpacing": 0,
            "strikeThrough": false
        }
    },
    "canUpdateUI": true,
    "centery": {
        "type": "string",
        "value": "50%"
    },
    "containerId": true,
    "containerweight": 100,
    "contentalignment": 4,
    "id": "lblColumn4Icon",
    "info": null,
    "ipad": {
        "psp": {
            "wrapping": 2
        }
    },
    "iphone": {
        "psp": {
            "wrapping": 2
        }
    },
    "isvisible": true,
    "kuid": "h09bd04e9f384a2faec08ef28f9c298e",
    "name": "kony.ui.Label",
    "paddinginpixel": false,
    "parent": "flxColumn4",
    "pf": "segReceivablePayableList1",
    "tooltip": "",
    "wType": "Label",
    "zindex": 1
}