{
    "AS_FlexContainer_d1e2e6a8d28e4b76a22d5225eefb2fba": {
        "id": "AS_FlexContainer_d1e2e6a8d28e4b76a22d5225eefb2fba",
        "type": "ACTION_SEQUENCE",
        "params": [{
            "datatype": "collection",
            "name": "eventobject"
        }, {
            "datatype": "collection",
            "name": "context"
        }],
        "contextObj": {
            "name": "segUserManagementFeaturePermissionsTablet",
            "type": "templates",
            "platform": "",
            "KUID": "d5da1ba04a1c4e3696de8119289e2ba2"
        },
        "language": "js",
        "actions": [{
            "id": "ADD_SNIPPET_dafbff24b899401fbcb65f3dfa58115e",
            "type": "ADD_SNIPPET",
            "codeSnippet": "this.selectOrUnselectParentFeature(eventobject, context);",
            "parentId": null
        }]
    }
}