{
    "AS_Form_i7d826f1f6ee43d781bcb3838edffd6c": {
        "id": "AS_Form_i7d826f1f6ee43d781bcb3838edffd6c",
        "type": "ACTION_SEQUENCE",
        "params": [{
            "datatype": "collection",
            "name": "eventobject"
        }],
        "contextObj": {
            "name": "frmUserManagement",
            "type": "forms",
            "platform": "",
            "KUID": "e89ee03e0666491aa06b82437adfbcbd"
        },
        "language": "js",
        "actions": [{
            "id": "ADD_SNIPPET__e67c3bc1192940c7bf00890b965f272a",
            "type": "ADD_SNIPPET",
            "codeSnippet": "this.initActions();",
            "parentId": null,
            "callbackType": null
        }]
    }
}