{
    "@class": "com.kony.gen.viz.model.component.KVizUserWidget",
    "DNDConfig": null,
    "_children_": [],
    "_height_": {
        "type": "ref",
        "value": "preferred"
    },
    "_left_": {
        "type": "string",
        "value": "0.00%"
    },
    "_margin_": [
        0,
        0,
        0,
        0
    ],
    "_orientation_": 1,
    "_padding_": [
        0,
        0,
        0,
        0
    ],
    "_percent_": true,
    "_render_": true,
    "_skin_": "s24c92fc23b14f5484b693ee9b8a9b35",
    "_top_": {
        "type": "string",
        "value": "150dp"
    },
    "_width_": {
        "type": "string",
        "value": "270dp"
    },
    "android": {},
    "androidwearos": {},
    "areflexpropsreferenced": false,
    "autogrowmode": 1,
    "canUpdateUI": true,
    "clipbounds": false,
    "containerweight": 0,
    "dataDiffs": {
        "AllForms": {
            "__events__": {},
            "__info__": {
                "isRoot": true,
                "kuid": "af0a970977a847adafc0c1aec7517084",
                "srcKUID": "aef6ac17436948abacbe12ea5a1d5e5b",
                "wType": "FlexContainer"
            },
            "isVisible": false,
            "left": {
                "Default": {
                    "type": "string",
                    "value": "0.00%"
                }
            },
            "responsiveData": {
                "b3": {
                    "right": {
                        "type": "string",
                        "value": "30dp"
                    },
                    "width": {
                        "type": "string",
                        "value": "270dp"
                    }
                },
                "b4": {
                    "isVisible": false
                }
            },
            "right": {},
            "top": {
                "Default": {
                    "type": "string",
                    "value": "150dp"
                }
            },
            "width": {
                "Default": {
                    "type": "string",
                    "value": "270dp"
                }
            },
            "zIndex": {
                "Default": 10
            }
        },
        "RichTextInfo": {
            "__events__": {},
            "__info__": {
                "kuid": "b1c72cfb69a0496bac562f26e048fc1c",
                "srcKUID": "i86f020750564f6ba173ce46ea601ab5",
                "wType": "RichText"
            },
            "i18n_text": "i18n.accounts.availableBalance",
            "isVisible": false,
            "responsiveData": {},
            "text": ""
        },
        "flxAccountType": {
            "__events__": {},
            "__info__": {
                "kuid": "c68388b22af34daeb384284bfac1293d",
                "srcKUID": "ed52287fd449401ba9a5f005c99e3f35",
                "wType": "FlexContainer"
            },
            "isVisible": true,
            "responsiveData": {},
            "top": {
                "Default": {
                    "type": "string",
                    "value": "-2dp"
                }
            }
        },
        "flxCross": {
            "__events__": {},
            "__info__": {
                "kuid": "eb89df3f553b463fa911d33e7a6df65d",
                "srcKUID": "d452c358ed1445a58e5fdff55685498f",
                "wType": "FlexContainer"
            },
            "centerY": {
                "Default": {
                    "type": "string",
                    "value": "31.54%"
                }
            },
            "right": {
                "Default": {
                    "type": "string",
                    "value": "5.55%"
                }
            }
        },
        "flxInformation": {
            "__events__": {},
            "__info__": {
                "kuid": "f62dca4a9ec24a68aa2eec0aeff6ba73",
                "srcKUID": "be414255ea60408894eb2a9b719b864e",
                "wType": "FlexContainer"
            },
            "autogrowMode": {
                "Default": 0
            },
            "clipBounds": false,
            "height": {
                "Default": {
                    "type": "string",
                    "value": "135dp"
                }
            },
            "left": {
                "Default": {
                    "type": "string",
                    "value": "1dp"
                }
            },
            "responsiveData": {
                "b1": {}
            },
            "top": {
                "Default": {
                    "type": "string",
                    "value": "0dp"
                }
            }
        },
        "flxInformationText": {
            "__events__": {},
            "__info__": {
                "kuid": "e1a731faf3fc4accbebf72f828fafffa",
                "srcKUID": "fa4dbab87ecf4647a21060118b02bd03",
                "wType": "FlexContainer"
            },
            "left": {
                "Default": {
                    "type": "string",
                    "value": "0dp"
                }
            },
            "responsiveData": {}
        },
        "imgCross": {
            "__events__": {},
            "__info__": {
                "kuid": "fae09662a17e471a8b438a3e2cc41760",
                "srcKUID": "d86a08cea857467eae13f42ed033a771",
                "wType": "Image"
            },
            "src": "icon_close_grey.png"
        },
        "imgToolTip": {
            "__events__": {},
            "__info__": {
                "kuid": "f9929f62b9a241cab56dde9b57f259e1",
                "srcKUID": "f9274528aa6b41bfb057f17c510b73b5",
                "wType": "Image"
            },
            "left": {
                "Default": {
                    "type": "string",
                    "value": "125px"
                }
            },
            "src": "tool_tip.png"
        },
        "lblInfo": {
            "__events__": {},
            "__info__": {
                "kuid": "de44fd22afb548389ac65a6dc8bd26cc",
                "srcKUID": "c6ecc9c129c943b396152e99a30763f6",
                "wType": "Label"
            },
            "centerY": {
                "Default": {
                    "type": "string",
                    "value": ""
                }
            },
            "responsiveData": {},
            "text": "Account Access defines whether the user will have access to <br> view accounts and create transactions for these accounts",
            "width": {
                "Default": {
                    "type": "string",
                    "value": "70%"
                }
            }
        },
        "lblSeperator": {
            "__events__": {},
            "__info__": {
                "kuid": "bb0c2bf5328f482bb434918007920ddd",
                "srcKUID": "f142d5aa44384a3fb94504a874cbbb95",
                "wType": "Label"
            }
        }
    },
    "desktopweb": {},
    "id": "InfoIconPopup",
    "info": null,
    "ipad": {},
    "iphone": {},
    "isdatareferenced": false,
    "isvisible": false,
    "kiosk": {},
    "kuid": "af0a970977a847adafc0c1aec7517084",
    "layouttype": 4,
    "masterType": 0,
    "name": "kony.ui.UserWidgetInstance",
    "parent": "frmCreateUserManually",
    "pf": "frmCreateUserManually",
    "responsiveData": {
        "b3": {
            "right": {
                "type": "string",
                "value": "30dp"
            },
            "width": {
                "type": "string",
                "value": "270dp"
            }
        },
        "b4": {}
    },
    "snaptogrid": true,
    "sourceUserWidget": "aef6ac17436948abacbe12ea5a1d5e5b",
    "spa": {},
    "spaan": {},
    "spaandroidtablet": {},
    "spabb": {},
    "spaip": {},
    "spaipad": {},
    "spamobile": {},
    "spatablet": {},
    "spawindowstablet": {},
    "spawinphone8": {},
    "tabrcandroid": {},
    "vizProps": {
        "hidewidgethierarchy": false
    },
    "vizprops": {
        "hidewidgethierarchy": false
    },
    "wType": "UserWidgetInstance",
    "windows10": {},
    "windows8": {},
    "winphone10": {},
    "winphone8": {},
    "zindex": 10
}