{
    "@class": "com.kony.gen.viz.model.component.KVizLabel",
    "DNDConfig": null,
    "__UDWInstanceModelForRender__": true,
    "_bottom_": {
        "type": "number",
        "value": ""
    },
    "_height_": {
        "type": "ref",
        "value": "preferred"
    },
    "_left_": {
        "type": "string",
        "value": "0"
    },
    "_margin_": [
        1,
        1,
        1,
        1
    ],
    "_padding_": [
        0,
        0,
        0,
        0
    ],
    "_skin_": "sff050dcdac74f41ac6dd121553d0127",
    "_text_": "Label",
    "_top_": {
        "type": "string",
        "value": "0"
    },
    "_width_": {
        "type": "ref",
        "value": "preferred"
    },
    "_wrapping_": 2,
    "android": {
        "textStyle": {
            "letterSpacing": 0,
            "strikeThrough": false
        }
    },
    "canUpdateUI": true,
    "containerweight": 100,
    "contentalignment": 4,
    "id": "lblDownloadOption",
    "info": null,
    "ipad": {
        "psp": {
            "wrapping": 2
        }
    },
    "iphone": {
        "psp": {
            "wrapping": 2
        }
    },
    "iscustomlayout": false,
    "isvisible": true,
    "kuid": "da3f0716054646ac86fa6a485be13787",
    "name": "kony.ui.Label",
    "parent": "flxDownloadServ",
    "pf": "frmPartialPaymentAcknowledgement",
    "responsiveData": {
        "b1": {
            "bottom": {
                "type": "string",
                "value": "0dp"
            },
            "skin": "s3e63ea9f083459c9fffb6971abc1020",
            "text": "D",
            "top": {
                "type": "string",
                "value": ""
            }
        },
        "b2": {
            "bottom": {
                "type": "string",
                "value": "0dp"
            },
            "skin": "s3e63ea9f083459c9fffb6971abc1020",
            "text": "D",
            "top": {
                "type": "string",
                "value": ""
            }
        },
        "b3": {
            "bottom": {
                "type": "string",
                "value": "0dp"
            },
            "skin": "s3e63ea9f083459c9fffb6971abc1020",
            "text": "D",
            "top": {
                "type": "string",
                "value": ""
            }
        },
        "b4": {
            "bottom": {
                "type": "string",
                "value": "0dp"
            },
            "skin": "s3e63ea9f083459c9fffb6971abc1020",
            "text": "D",
            "top": {
                "type": "string",
                "value": ""
            }
        }
    },
    "retaincontentalignment": false,
    "retainflexpositionproperties": false,
    "tooltip": "",
    "wType": "Label"
}