{
    "DNDConfig": null,
    "_height_": {
        "type": "string",
        "value": "30dp"
    },
    "_left_": {
        "type": "string",
        "value": "0"
    },
    "_margin_": [
        0,
        0,
        0,
        0
    ],
    "_orientation_": 6,
    "_padding_": [
        0,
        0,
        0,
        0
    ],
    "_percent_": true,
    "_skin_": "scb8be6808294b1d8d7e5d3d3f7e10c5",
    "_top_": {
        "type": "string",
        "value": "1.82%"
    },
    "_width_": {
        "type": "string",
        "value": "30.95%"
    },
    "activeNativeBorderCornerRadiusControl": "topRightControl",
    "allboxes": [],
    "autogrowmode": 0,
    "canUpdateUI": true,
    "centery": {
        "type": "string",
        "value": "50%"
    },
    "children": [
        "lblPending"
    ],
    "clipbounds": false,
    "containerweight": 100,
    "enablescrolling": true,
    "id": "flxPending",
    "info": null,
    "iscustomlayout": false,
    "isvisible": true,
    "kuid": "i3acf15dc1434c28b2655880bb74bda2",
    "layouttype": 2,
    "name": "kony.ui.FlexContainer",
    "parent": "flxMenuContent",
    "pf": "userwidgetmodel",
    "retaincontentalignment": false,
    "retainflexpositionproperties": false,
    "retainflowhorizontalalignment": false,
    "snapgridsize": 10,
    "snaptogrid": true,
    "wType": "FlexContainer",
    "widgetalignment": 1,
    "zindex": 2
}