{
    "DNDConfig": null,
    "_height_": {
        "type": "string",
        "value": "100%"
    },
    "_left_": {
        "type": "string",
        "value": "0dp"
    },
    "_margin_": [
        0,
        0,
        0,
        0
    ],
    "_orientation_": 6,
    "_padding_": [
        0,
        0,
        0,
        0
    ],
    "_percent_": true,
    "_skin_": "sec7cce05f18492ea7d1ed7dedec84cf",
    "_top_": {
        "type": "string",
        "value": "0dp"
    },
    "_width_": {
        "type": "string",
        "value": "25%"
    },
    "allboxes": [],
    "autogrowmode": 0,
    "canUpdateUI": true,
    "children": [
        "lblSummary0",
        "lblCount0",
        "lblStatusAmount0"
    ],
    "clipbounds": false,
    "containerweight": 100,
    "enablescrolling": true,
    "id": "flxSummary0",
    "info": null,
    "iscustomlayout": false,
    "isvisible": true,
    "kuid": "d2e7e7f546b7480c8f8edc9581d91a13",
    "layouttype": 4,
    "name": "kony.ui.FlexContainer",
    "parent": "flxImportStatusSummary",
    "pf": "userwidgetmodel",
    "retaincontentalignment": false,
    "retainflexpositionproperties": false,
    "retainflowhorizontalalignment": false,
    "snapgridsize": 10,
    "snaptogrid": true,
    "wType": "FlexContainer",
    "widgetalignment": 1
}