{
    "DNDConfig": null,
    "_height_": {
        "type": "string",
        "value": "210dp"
    },
    "_left_": {
        "type": "string",
        "value": "50dp"
    },
    "_margin_": [
        0,
        0,
        0,
        0
    ],
    "_orientation_": 6,
    "_padding_": [
        0,
        0,
        0,
        0
    ],
    "_percent_": true,
    "_right_": {
        "type": "string",
        "value": "49dp"
    },
    "_skin_": "s62114c86c264411a843a5c6cff1ef08",
    "_top_": {
        "type": "string",
        "value": "0"
    },
    "_width_": {
        "type": "string",
        "value": "218dp"
    },
    "allboxes": [],
    "canUpdateUI": true,
    "children": [
        "flxhealthGraph"
    ],
    "clipbounds": false,
    "containerweight": 100,
    "enablescrolling": true,
    "id": "flxGraph",
    "info": null,
    "iscustomlayout": false,
    "isvisible": true,
    "kuid": "a5ac07f8aa9241a18320b0386943a32d",
    "layouttype": 3,
    "name": "kony.ui.FlexContainer",
    "parent": "flxRight",
    "pf": "userwidgetmodel",
    "responsiveData": {
        "b2": {
            "height": {
                "type": "string",
                "value": "169dp"
            },
            "left": {
                "type": "string",
                "value": "8dp"
            },
            "right": {
                "type": "string",
                "value": "0dp"
            },
            "top": {
                "type": "string",
                "value": "0dp"
            },
            "width": {
                "type": "string",
                "value": "169dp"
            }
        }
    },
    "retaincontentalignment": false,
    "retainflexpositionproperties": false,
    "retainflowhorizontalalignment": false,
    "snapgridsize": 10,
    "snaptogrid": true,
    "wType": "FlexContainer",
    "widgetalignment": 1
}